intent_classification/IntentModel.py
intent_classification/__init__.py
intent_classification/intent_classification_module.py
intent_classification/dict/__init__.py
intent_classification/dict/bind_dict.py
intent_classification/train_tools/__init__.py
intent_classification/train_tools/create_dict.py
intent_classification/utils/Preprocess.py
intent_classification/utils/__init__.py
intent_classification_filab-0.0.1.1.dist-info/LICENSE
intent_classification_filab-0.0.1.1.dist-info/METADATA
intent_classification_filab-0.0.1.1.dist-info/WHEEL
intent_classification_filab-0.0.1.1.dist-info/top_level.txt
intent_classification_filab-0.0.1.1.dist-info/RECORD
