Metadata-Version: 2.1
Name: intent_classification_filab
Version: 0.0.1.1
Summary: 사용자 입력에 대하여 의도 분석을 하는 프로그램입니다.
Author: jackaa
Author-email: jackaa <jackaa@filab.co.kr>
Classifier: Programming Language :: Python :: 3
Classifier: License :: OSI Approved :: MIT License
Classifier: Operating System :: OS Independent
Requires-Python: >=3.9
License-File: LICENSE
